{
  "count": 3,
  "cursor": 1780591819,
  "data": [
    {
      "AvailabilityTrips": [
        {
          "AvailabilityID": "32qhYr1xwspv0NZV06r4OELNRFM",
          "Cabin": "economy",
          "Carriers": "AS",
          "ID": "3BkvygkY5yV1fjV2wiCdS1KbnQc",
          "MileageCost": 27500,
          "RemainingSeats": 9,
          "Stops": 1,
          "TotalDuration": 497,
          "TotalTaxes": 1120
        },
        {
          "AvailabilityID": "32qhYr1xwspv0NZV06r4OELNRFM",
          "Cabin": "economy",
          "Carriers": "AS",
          "ID": "3DE0pCyiNOMFmg0Y19PUyCsAA0E",
          "MileageCost": 27500,
          "RemainingSeats": 9,
          "Stops": 1,
          "TotalDuration": 959,
          "TotalTaxes": 1120
        },
        {
          "AvailabilityID": "32qhYr1xwspv0NZV06r4OELNRFM",
          "Cabin": "economy",
          "Carriers": "AS",
          "ID": "3BkvykGMMD6LE2DVG3nAqN8vXyJ",
          "MileageCost": 27500,
          "RemainingSeats": 9,
          "Stops": 1,
          "TotalDuration": 322,
          "TotalTaxes": 560
        },
        {
          "AvailabilityID": "32qhYr1xwspv0NZV06r4OELNRFM",
          "Cabin": "business",
          "Carriers": "AS",
          "ID": "3BkvyjFZjSvDGDT5JpughBZr3Vr",
          "MileageCost": 47500,
          "RemainingSeats": 9,
          "Stops": 1,
          "TotalDuration": 322,
          "TotalTaxes": 560
        },
        {
          "AvailabilityID": "32qhYr1xwspv0NZV06r4OELNRFM",
          "Cabin": "business",
          "Carriers": "AS",
          "ID": "3BkvyhZaChR8KTAaZ0p38sguDKt",
          "MileageCost": 47500,
          "RemainingSeats": 9,
          "Stops": 1,
          "TotalDuration": 497,
          "TotalTaxes": 1120
        },
        {
          "AvailabilityID": "32qhYr1xwspv0NZV06r4OELNRFM",
          "Cabin": "business",
          "Carriers": "AS",
          "ID": "3DE0pB87wZS31XHLAoe23ZUu7jg",
          "MileageCost": 47500,
          "RemainingSeats": 9,
          "Stops": 1,
          "TotalDuration": 959,
          "TotalTaxes": 1120
        },
        {
          "AvailabilityID": "32qhYr1xwspv0NZV06r4OELNRFM",
          "Cabin": "business",
          "Carriers": "AA",
          "ID": "3DE0p7BQFHtAjtOTo9JM3MB70p3",
          "MileageCost": 20000,
          "RemainingSeats": 2,
          "Stops": 1,
          "TotalDuration": 560,
          "TotalTaxes": 2370
        },
        {
          "AvailabilityID": "32qhYr1xwspv0NZV06r4OELNRFM",
          "Cabin": "economy",
          "Carriers": "AS",
          "ID": "3BkvyfNYkg0jOVT74gusu5khPXj",
          "MileageCost": 27500,
          "RemainingSeats": 9,
          "Stops": 1,
          "TotalDuration": 437,
          "TotalTaxes": 560
        },
        {
          "AvailabilityID": "32qhYr1xwspv0NZV06r4OELNRFM",
          "Cabin": "economy",
          "Carriers": "AS",
          "ID": "3BkvyhcPpCtzYhaIJ6fo8HscGuX",
          "MileageCost": 27500,
          "RemainingSeats": 9,
          "Stops": 1,
          "TotalDuration": 262,
          "TotalTaxes": 560
        },
        {
          "AvailabilityID": "32qhYr1xwspv0NZV06r4OELNRFM",
          "Cabin": "economy",
          "Carriers": "AS",
          "ID": "3DE0pDH0S2x4L52OfTjuYvQrDqD",
          "MileageCost": 27500,
          "RemainingSeats": 9,
          "Stops": 1,
          "TotalDuration": 899,
          "TotalTaxes": 1120
        },
        {
          "AvailabilityID": "32qhYr1xwspv0NZV06r4OELNRFM",
          "Cabin": "business",
          "Carriers": "AS",
          "ID": "3BkvyiXFhV0U14UiOyE3cqZ8wGj",
          "MileageCost": 47500,
          "RemainingSeats": 8,
          "Stops": 1,
          "TotalDuration": 437,
          "TotalTaxes": 560
        },
        {
          "AvailabilityID": "32qhYr1xwspv0NZV06r4OELNRFM",
          "Cabin": "business",
          "Carriers": "AS",
          "ID": "3DE0pAG5ngpc0szIpf9gGvmsghV",
          "MileageCost": 47500,
          "RemainingSeats": 8,
          "Stops": 1,
          "TotalDuration": 899,
          "TotalTaxes": 1120
        },
        {
          "AvailabilityID": "32qhYr1xwspv0NZV06r4OELNRFM",
          "Cabin": "business",
          "Carriers": "AS",
          "ID": "3BkvyhPAVFKqMnWwc3BznG65gOP",
          "MileageCost": 47500,
          "RemainingSeats": 8,
          "Stops": 1,
          "TotalDuration": 262,
          "TotalTaxes": 560
        },
        {
          "AvailabilityID": "32qhYr1xwspv0NZV06r4OELNRFM",
          "Cabin": "economy",
          "Carriers": "AS",
          "ID": "3DE0p6HcLZEx5pW3dTTGKdUhsUK",
          "MileageCost": 15000,
          "RemainingSeats": 8,
          "Stops": 2,
          "TotalDuration": 894,
          "TotalTaxes": 1120
        },
        {
          "AvailabilityID": "32qhYr1xwspv0NZV06r4OELNRFM",
          "Cabin": "business",
          "Carriers": "AS",
          "ID": "3DE0p5i0d3zuZyDmYkcumqHXsl2",
          "MileageCost": 37500,
          "RemainingSeats": 2,
          "Stops": 2,
          "TotalDuration": 894,
          "TotalTaxes": 1120
        },
        {
          "AvailabilityID": "32qhYr1xwspv0NZV06r4OELNRFM",
          "Cabin": "economy",
          "Carriers": "AS",
          "ID": "3DE0p7429vnwBC1kkh1f7sBLFgD",
          "MileageCost": 15000,
          "RemainingSeats": 9,
          "Stops": 2,
          "TotalDuration": 879,
          "TotalTaxes": 1120
        },
        {
          "AvailabilityID": "32qhYr1xwspv0NZV06r4OELNRFM",
          "Cabin": "economy",
          "Carriers": "AS",
          "ID": "3BkvyiuQsjzwv5L8GuxhuNPLc6l",
          "MileageCost": 15000,
          "RemainingSeats": 9,
          "Stops": 2,
          "TotalDuration": 417,
          "TotalTaxes": 560
        },
        {
          "AvailabilityID": "32qhYr1xwspv0NZV06r4OELNRFM",
          "Cabin": "economy",
          "Carriers": "AS",
          "ID": "3DE0p7MLDEGqKFT6s6QbljCqLmM",
          "MileageCost": 15000,
          "RemainingSeats": 9,
          "Stops": 2,
          "TotalDuration": 879,
          "TotalTaxes": 1120
        },
        {
          "AvailabilityID": "32qhYr1xwspv0NZV06r4OELNRFM",
          "Cabin": "economy",
          "Carriers": "AS",
          "ID": "3DE0pB9qmaUZJbxe5zIW55t7ANr",
          "MileageCost": 15000,
          "RemainingSeats": 9,
          "Stops": 2,
          "TotalDuration": 879,
          "TotalTaxes": 1120
        },
        {
          "AvailabilityID": "32qhYr1xwspv0NZV06r4OELNRFM",
          "Cabin": "economy",
          "Carriers": "AS",
          "ID": "3BkvyigEbxXATfclJ3rp9Q2RgUH",
          "MileageCost": 22500,
          "RemainingSeats": 9,
          "Stops": 1,
          "TotalDuration": 305,
          "TotalTaxes": 560
        },
        {
          "AvailabilityID": "32qhYr1xwspv0NZV06r4OELNRFM",
          "Cabin": "business",
          "Carriers": "AS",
          "ID": "3Bkvyj9TqLzJRAtlqtIqv2BF3Ur",
          "MileageCost": 47500,
          "RemainingSeats": 9,
          "Stops": 2,
          "TotalDuration": 417,
          "TotalTaxes": 560
        },
        {
          "AvailabilityID": "32qhYr1xwspv0NZV06r4OELNRFM",
          "Cabin": "business",
          "Carriers": "AS",
          "ID": "3DE0pA4WxbykHcGMxpGjZzAHdvl",
          "MileageCost": 47500,
          "RemainingSeats": 9,
          "Stops": 2,
          "TotalDuration": 879,
          "TotalTaxes": 1120
        },
        {
          "AvailabilityID": "32qhYr1xwspv0NZV06r4OELNRFM",
          "Cabin": "business",
          "Carriers": "AS",
          "ID": "3DE0p7Xm9sITupXRRIWiY0BUB0v",
          "MileageCost": 47500,
          "RemainingSeats": 9,
          "Stops": 2,
          "TotalDuration": 879,
          "TotalTaxes": 1120
        },
        {
          "AvailabilityID": "32qhYr1xwspv0NZV06r4OELNRFM",
          "Cabin": "business",
          "Carriers": "AS",
          "ID": "3DE0p5l56oFXd4TckN3t3ObkPZF",
          "MileageCost": 47500,
          "RemainingSeats": 9,
          "Stops": 2,
          "TotalDuration": 879,
          "TotalTaxes": 1120
        },
        {
          "AvailabilityID": "32qhYr1xwspv0NZV06r4OELNRFM",
          "Cabin": "business",
          "Carriers": "AS",
          "ID": "3Bkvyffm7Wj89i8xmk0Oft5xvwW",
          "MileageCost": 47500,
          "RemainingSeats": 9,
          "Stops": 1,
          "TotalDuration": 305,
          "TotalTaxes": 560
        },
        {
          "AvailabilityID": "32qhYr1xwspv0NZV06r4OELNRFM",
          "Cabin": "economy",
          "Carriers": "AS",
          "ID": "3DE0p9B6EyvbOHUFpnKOIPEQKaw",
          "MileageCost": 15000,
          "RemainingSeats": 9,
          "Stops": 2,
          "TotalDuration": 819,
          "TotalTaxes": 1120
        },
        {
          "AvailabilityID": "32qhYr1xwspv0NZV06r4OELNRFM",
          "Cabin": "economy",
          "Carriers": "AS",
          "ID": "3DE0p6XryQvGkgsQUSa094B8n3q",
          "MileageCost": 15000,
          "RemainingSeats": 9,
          "Stops": 2,
          "TotalDuration": 819,
          "TotalTaxes": 1120
        },
        {
          "AvailabilityID": "32qhYr1xwspv0NZV06r4OELNRFM",
          "Cabin": "economy",
          "Carriers": "AS",
          "ID": "3DE0pApFQYQC9l8inamlD37hFnw",
          "MileageCost": 15000,
          "RemainingSeats": 9,
          "Stops": 2,
          "TotalDuration": 819,
          "TotalTaxes": 1120
        },
        {
          "AvailabilityID": "32qhYr1xwspv0NZV06r4OELNRFM",
          "Cabin": "economy",
          "Carriers": "AS",
          "ID": "3BkvyiyXuLgvATe0C98eCxQMGeQ",
          "MileageCost": 15000,
          "RemainingSeats": 9,
          "Stops": 2,
          "TotalDuration": 357,
          "TotalTaxes": 560
        },
        {
          "AvailabilityID": "32qhYr1xwspv0NZV06r4OELNRFM",
          "Cabin": "business",
          "Carriers": "AS",
          "ID": "3DE0pA06TSpqMS6rGIFolTbSIaG",
          "MileageCost": 47500,
          "RemainingSeats": 9,
          "Stops": 2,
          "TotalDuration": 819,
          "TotalTaxes": 1120
        },
        {
          "AvailabilityID": "32qhYr1xwspv0NZV06r4OELNRFM",
          "Cabin": "business",
          "Carriers": "AS",
          "ID": "3DE0p7qCyfyvbT1b41S7208lsna",
          "MileageCost": 47500,
          "RemainingSeats": 9,
          "Stops": 2,
          "TotalDuration": 819,
          "TotalTaxes": 1120
        },
        {
          "AvailabilityID": "32qhYr1xwspv0NZV06r4OELNRFM",
          "Cabin": "business",
          "Carriers": "AS",
          "ID": "3Bkvyej01MMSmOm8Jn0z5BFNYgF",
          "MileageCost": 47500,
          "RemainingSeats": 9,
          "Stops": 2,
          "TotalDuration": 357,
          "TotalTaxes": 560
        },
        {
          "AvailabilityID": "32qhYr1xwspv0NZV06r4OELNRFM",
          "Cabin": "business",
          "Carriers": "AS",
          "ID": "3DE0pCBUQzPp0AxBUWdwXCxFv7E",
          "MileageCost": 47500,
          "RemainingSeats": 9,
          "Stops": 2,
          "TotalDuration": 819,
          "TotalTaxes": 1120
        },
        {
          "AvailabilityID": "32qhYr1xwspv0NZV06r4OELNRFM",
          "Cabin": "economy",
          "Carriers": "AS",
          "ID": "3DE0pB2SO29IJXuybcqzUxe5EGx",
          "MileageCost": 32500,
          "RemainingSeats": 9,
          "Stops": 1,
          "TotalDuration": 779,
          "TotalTaxes": 1120
        },
        {
          "AvailabilityID": "32qhYr1xwspv0NZV06r4OELNRFM",
          "Cabin": "economy",
          "Carriers": "AS",
          "ID": "3BkvykgsWwx2AGA7dodZ5y3au6H",
          "MileageCost": 32500,
          "RemainingSeats": 9,
          "Stops": 1,
          "TotalDuration": 317,
          "TotalTaxes": 560
        },
        {
          "AvailabilityID": "32qhYr1xwspv0NZV06r4OELNRFM",
          "Cabin": "business",
          "Carriers": "AS",
          "ID": "3DE0pD1whZrWfAnWEe8f8nN8u44",
          "MileageCost": 47500,
          "RemainingSeats": 8,
          "Stops": 1,
          "TotalDuration": 779,
          "TotalTaxes": 1120
        },
        {
          "AvailabilityID": "32qhYr1xwspv0NZV06r4OELNRFM",
          "Cabin": "business",
          "Carriers": "AS",
          "ID": "3Bkvyga5d0b0jMfihyQ8cYLiXtV",
          "MileageCost": 47500,
          "RemainingSeats": 8,
          "Stops": 1,
          "TotalDuration": 317,
          "TotalTaxes": 560
        },
        {
          "AvailabilityID": "32qhYr1xwspv0NZV06r4OELNRFM",
          "Cabin": "economy",
          "Carriers": "AS",
          "ID": "3DE0p5YPcJrHzqEsg6S3Rt8xLAA",
          "MileageCost": 15000,
          "RemainingSeats": 7,
          "Stops": 2,
          "TotalDuration": 752,
          "TotalTaxes": 1120
        },
        {
          "AvailabilityID": "32qhYr1xwspv0NZV06r4OELNRFM",
          "Cabin": "business",
          "Carriers": "AS",
          "ID": "3DE0p8afJeQgU0VDpfuQzt0hiI3",
          "MileageCost": 37500,
          "RemainingSeats": 2,
          "Stops": 2,
          "TotalDuration": 752,
          "TotalTaxes": 1120
        },
        {
          "AvailabilityID": "32qhYr1xwspv0NZV06r4OELNRFM",
          "Cabin": "economy",
          "Carriers": "AS",
          "ID": "3DE0pB6JFZYo0fsOOkBq5jvC2uk",
          "MileageCost": 15000,
          "RemainingSeats": 8,
          "Stops": 2,
          "TotalDuration": 687,
          "TotalTaxes": 560
        },
        {
          "AvailabilityID": "32qhYr1xwspv0NZV06r4OELNRFM",
          "Cabin": "business",
          "Carriers": "AS",
          "ID": "3DE0p7YBPAOyp6CpBUKTDe0fAFm",
          "MileageCost": 37500,
          "RemainingSeats": 2,
          "Stops": 2,
          "TotalDuration": 687,
          "TotalTaxes": 560
        },
        {
          "AvailabilityID": "32qhYr1xwspv0NZV06r4OELNRFM",
          "Cabin": "economy",
          "Carriers": "AS",
          "ID": "3DE0pALjkzJ03pDYygzybcUDMgz",
          "MileageCost": 15000,
          "RemainingSeats": 9,
          "Stops": 2,
          "TotalDuration": 647,
          "TotalTaxes": 1120
        },
        {
          "AvailabilityID": "32qhYr1xwspv0NZV06r4OELNRFM",
          "Cabin": "economy",
          "Carriers": "AS",
          "ID": "3DE0p5pOBSUafszsdJ0QGLWPbmw",
          "MileageCost": 15000,
          "RemainingSeats": 9,
          "Stops": 2,
          "TotalDuration": 647,
          "TotalTaxes": 560
        },
        {
          "AvailabilityID": "32qhYr1xwspv0NZV06r4OELNRFM",
          "Cabin": "business",
          "Carriers": "AS",
          "ID": "3DE0p5qDqveRMOQqdekFz6Db37i",
          "MileageCost": 37500,
          "RemainingSeats": 4,
          "Stops": 2,
          "TotalDuration": 647,
          "TotalTaxes": 560
        },
        {
          "AvailabilityID": "32qhYr1xwspv0NZV06r4OELNRFM",
          "Cabin": "business",
          "Carriers": "AS",
          "ID": "3DE0p6fmAIS4vRDdpzK8mPLtdUh",
          "MileageCost": 37500,
          "RemainingSeats": 4,
          "Stops": 2,
          "TotalDuration": 647,
          "TotalTaxes": 1120
        },
        {
          "AvailabilityID": "32qhYr1xwspv0NZV06r4OELNRFM",
          "Cabin": "economy",
          "Carriers": "AS",
          "ID": "3DE0pDC4LAi8umYLzEZDR2P13Y6",
          "MileageCost": 27500,
          "RemainingSeats": 9,
          "Stops": 2,
          "TotalDuration": 621,
          "TotalTaxes": 560
        },
        {
          "AvailabilityID": "32qhYr1xwspv0NZV06r4OELNRFM",
          "Cabin": "business",
          "Carriers": "AS",
          "ID": "3DE0p7hAEW7lqFvnj3e9ElmANlL",
          "MileageCost": 37500,
          "RemainingSeats": 2,
          "Stops": 2,
          "TotalDuration": 621,
          "TotalTaxes": 560
        },
        {
          "AvailabilityID": "32qhYr1xwspv0NZV06r4OELNRFM",
          "Cabin": "economy",
          "Carriers": "AS",
          "ID": "3DE0p6Ue2vyhjbUrRR0xdC35zEn",
          "MileageCost": 22500,
          "RemainingSeats": 9,
          "Stops": 2,
          "TotalDuration": 609,
          "TotalTaxes": 560
        },
        {
          "AvailabilityID": "32qhYr1xwspv0NZV06r4OELNRFM",
          "Cabin": "business",
          "Carriers": "AS",
          "ID": "3DE0p8THfJlL0Oj60qRnZQhRxKy",
          "MileageCost": 67500,
          "RemainingSeats": 9,
          "Stops": 2,
          "TotalDuration": 609,
          "TotalTaxes": 560
        },
        {
          "AvailabilityID": "32qhYr1xwspv0NZV06r4OELNRFM",
          "Cabin": "economy",
          "Carriers": "AS",
          "ID": "3DE0p9Gqy6G6hN7aJmZrOiF8vtG",
          "MileageCost": 22500,
          "RemainingSeats": 9,
          "Stops": 2,
          "TotalDuration": 607,
          "TotalTaxes": 560
        },
        {
          "AvailabilityID": "32qhYr1xwspv0NZV06r4OELNRFM",
          "Cabin": "economy",
          "Carriers": "AS",
          "ID": "3DE0pCN39EdL2wY1nXCbNSvqwcY",
          "MileageCost": 22500,
          "RemainingSeats": 9,
          "Stops": 2,
          "TotalDuration": 607,
          "TotalTaxes": 1120
        },
        {
          "AvailabilityID": "32qhYr1xwspv0NZV06r4OELNRFM",
          "Cabin": "business",
          "Carriers": "AS",
          "ID": "3DE0pCpV5pBaFPg9iVuMMCEzoHU",
          "MileageCost": 47500,
          "RemainingSeats": 9,
          "Stops": 2,
          "TotalDuration": 607,
          "TotalTaxes": 560
        },
        {
          "AvailabilityID": "32qhYr1xwspv0NZV06r4OELNRFM",
          "Cabin": "business",
          "Carriers": "AS",
          "ID": "3DE0pBX1lKFaCTIEfpJHHaDV0lM",
          "MileageCost": 47500,
          "RemainingSeats": 7,
          "Stops": 2,
          "TotalDuration": 607,
          "TotalTaxes": 1120
        },
        {
          "AvailabilityID": "32qhYr1xwspv0NZV06r4OELNRFM",
          "Cabin": "economy",
          "Carriers": "AS",
          "ID": "3DE0p5tsZkFiS0SswxlrNN1qsIf",
          "MileageCost": 32500,
          "RemainingSeats": 9,
          "Stops": 1,
          "TotalDuration": 589,
          "TotalTaxes": 1120
        },
        {
          "AvailabilityID": "32qhYr1xwspv0NZV06r4OELNRFM",
          "Cabin": "business",
          "Carriers": "AS",
          "ID": "3DE0pB849c6mZT9ubN6ugrJ9VfK",
          "MileageCost": 47500,
          "RemainingSeats": 8,
          "Stops": 1,
          "TotalDuration": 589,
          "TotalTaxes": 1120
        },
        {
          "AvailabilityID": "32qhYr1xwspv0NZV06r4OELNRFM",
          "Cabin": "economy",
          "Carriers": "AS",
          "ID": "3DE0pCPupxmIKGfW4Ryf9Gn8xMO",
          "MileageCost": 32500,
          "RemainingSeats": 9,
          "Stops": 2,
          "TotalDuration": 509,
          "TotalTaxes": 560
        },
        {
          "AvailabilityID": "32qhYr1xwspv0NZV06r4OELNRFM",
          "Cabin": "business",
          "Carriers": "AS",
          "ID": "3DE0p5v0sg9YpZF6SBZ3ThzLIEH",
          "MileageCost": 47500,
          "RemainingSeats": 1,
          "Stops": 2,
          "TotalDuration": 509,
          "TotalTaxes": 560
        },
        {
          "AvailabilityID": "32qhYr1xwspv0NZV06r4OELNRFM",
          "Cabin": "economy",
          "Carriers": "AS",
          "ID": "3DE0p6LKy67eNDZaFZ5e9g6oGQC",
          "MileageCost": 27500,
          "RemainingSeats": 9,
          "Stops": 2,
          "TotalDuration": 449,
          "TotalTaxes": 560
        },
        {
          "AvailabilityID": "32qhYr1xwspv0NZV06r4OELNRFM",
          "Cabin": "business",
          "Carriers": "AS",
          "ID": "3DE0p67fT5oRYJGBCe7k9LhoEyo",
          "MileageCost": 47500,
          "RemainingSeats": 2,
          "Stops": 2,
          "TotalDuration": 449,
          "TotalTaxes": 560
        },
        {
          "AvailabilityID": "32qhYr1xwspv0NZV06r4OELNRFM",
          "Cabin": "economy",
          "Carriers": "AS",
          "ID": "3DE0pAzqTFD4gwG11Yu39MviIXN",
          "MileageCost": 15000,
          "RemainingSeats": 9,
          "Stops": 2,
          "TotalDuration": 419,
          "TotalTaxes": 560
        },
        {
          "AvailabilityID": "32qhYr1xwspv0NZV06r4OELNRFM",
          "Cabin": "business",
          "Carriers": "AS",
          "ID": "3DE0pAgnbu7A0fqt9NMKE5a8eln",
          "MileageCost": 47500,
          "RemainingSeats": 9,
          "Stops": 2,
          "TotalDuration": 419,
          "TotalTaxes": 560
        },
        {
          "AvailabilityID": "32qhYr1xwspv0NZV06r4OELNRFM",
          "Cabin": "economy",
          "Carriers": "AS",
          "ID": "3DE0pCaXJHCbEgLXg1RY0TV0WUO",
          "MileageCost": 27500,
          "RemainingSeats": 1,
          "Stops": 1,
          "TotalDuration": 396,
          "TotalTaxes": 560
        },
        {
          "AvailabilityID": "32qhYr1xwspv0NZV06r4OELNRFM",
          "Cabin": "business",
          "Carriers": "AS",
          "ID": "3DE0p94dPnsKoZLgffP8ne63ZFz",
          "MileageCost": 47500,
          "RemainingSeats": 7,
          "Stops": 1,
          "TotalDuration": 396,
          "TotalTaxes": 560
        },
        {
          "AvailabilityID": "32qhYr1xwspv0NZV06r4OELNRFM",
          "Cabin": "economy",
          "Carriers": "AS",
          "ID": "3DE0pAgHT6Yckhr9dRDKTWtiKeW",
          "MileageCost": 27500,
          "RemainingSeats": 9,
          "Stops": 1,
          "TotalDuration": 316,
          "TotalTaxes": 560
        },
        {
          "AvailabilityID": "32qhYr1xwspv0NZV06r4OELNRFM",
          "Cabin": "business",
          "Carriers": "AS",
          "ID": "3DE0p6Lr0OGvbNWlLVz7qubRGT8",
          "MileageCost": 47500,
          "RemainingSeats": 6,
          "Stops": 1,
          "TotalDuration": 316,
          "TotalTaxes": 560
        },
        {
          "AvailabilityID": "32qhYr1xwspv0NZV06r4OELNRFM",
          "Cabin": "economy",
          "Carriers": "AS",
          "ID": "3DE0p7XFEgoE5w0TgPei62Ah8Eg",
          "MileageCost": 15000,
          "RemainingSeats": 9,
          "Stops": 2,
          "TotalDuration": 960,
          "TotalTaxes": 1120
        },
        {
          "AvailabilityID": "32qhYr1xwspv0NZV06r4OELNRFM",
          "Cabin": "business",
          "Carriers": "AS",
          "ID": "3DE0p7MMe3Br49uL87uKutqfNVi",
          "MileageCost": 37500,
          "RemainingSeats": 4,
          "Stops": 2,
          "TotalDuration": 960,
          "TotalTaxes": 1120
        }
      ],
      "CreatedAt": "2025-09-18T00:05:36.981909Z",
      "Date": "2026-09-05",
      "FAirlines": "",
      "FAirlinesRaw": "",
      "FAvailable": false,
      "FAvailableRaw": false,
      "FDirect": false,
      "FDirectAirlines": "",
      "FDirectAirlinesRaw": "",
      "FDirectMileageCost": 0,
      "FDirectMileageCostRaw": 0,
      "FDirectRaw": false,
      "FDirectRemainingSeats": 0,
      "FDirectRemainingSeatsRaw": 0,
      "FDirectTotalTaxes": 0,
      "FDirectTotalTaxesRaw": 0,
      "FMileageCost": "0",
      "FMileageCostRaw": 0,
      "FRemainingSeats": 0,
      "FRemainingSeatsRaw": 0,
      "FTotalTaxes": 0,
      "FTotalTaxesRaw": 0,
      "ID": "32qhYr1xwspv0NZV06r4OELNRFM",
      "JAirlines": "AA, AS",
      "JAirlinesRaw": "AA, AS",
      "JAvailable": true,
      "JAvailableRaw": true,
      "JDirect": false,
      "JDirectAirlines": "",
      "JDirectAirlinesRaw": "",
      "JDirectMileageCost": 0,
      "JDirectMileageCostRaw": 0,
      "JDirectRaw": false,
      "JDirectRemainingSeats": 0,
      "JDirectRemainingSeatsRaw": 0,
      "JDirectTotalTaxes": 0,
      "JDirectTotalTaxesRaw": 0,
      "JMileageCost": "20000",
      "JMileageCostRaw": 20000,
      "JRemainingSeats": 9,
      "JRemainingSeatsRaw": 9,
      "JTotalTaxes": 2370,
      "JTotalTaxesRaw": 2370,
      "ParsedDate": "2026-09-05T00:00:00Z",
      "Route": {
        "DestinationAirport": "MSO",
        "DestinationRegion": "North America",
        "Distance": 769,
        "ID": "2XVqe9jpLUmK8gzefTtbEZ79DUc",
        "OriginAirport": "SFO",
        "OriginRegion": "North America",
        "Source": "alaska"
      },
      "RouteID": "2XVqe9jpLUmK8gzefTtbEZ79DUc",
      "Source": "alaska",
      "TaxesCurrency": "USD",
      "UpdatedAt": "2026-05-03T18:15:01.636793Z",
      "WAirlines": "",
      "WAirlinesRaw": "",
      "WAvailable": false,
      "WAvailableRaw": false,
      "WDirect": false,
      "WDirectAirlines": "",
      "WDirectAirlinesRaw": "",
      "WDirectMileageCost": 0,
      "WDirectMileageCostRaw": 0,
      "WDirectRaw": false,
      "WDirectRemainingSeats": 0,
      "WDirectRemainingSeatsRaw": 0,
      "WDirectTotalTaxes": 0,
      "WDirectTotalTaxesRaw": 0,
      "WMileageCost": "0",
      "WMileageCostRaw": 0,
      "WRemainingSeats": 0,
      "WRemainingSeatsRaw": 0,
      "WTotalTaxes": 0,
      "WTotalTaxesRaw": 0,
      "YAirlines": "AS",
      "YAirlinesRaw": "AS",
      "YAvailable": true,
      "YAvailableRaw": true,
      "YDirect": false,
      "YDirectAirlines": "",
      "YDirectAirlinesRaw": "",
      "YDirectMileageCost": 0,
      "YDirectMileageCostRaw": 0,
      "YDirectRaw": false,
      "YDirectRemainingSeats": 0,
      "YDirectRemainingSeatsRaw": 0,
      "YDirectTotalTaxes": 0,
      "YDirectTotalTaxesRaw": 0,
      "YMileageCost": "15000",
      "YMileageCostRaw": 15000,
      "YRemainingSeats": 9,
      "YRemainingSeatsRaw": 9,
      "YTotalTaxes": 560,
      "YTotalTaxesRaw": 560
    },
    {
      "AvailabilityTrips": [
        {
          "AvailabilityID": "32qhZ530xETR57J6czXefZfujys",
          "Cabin": "economy",
          "Carriers": "UA",
          "ID": "3CyvHi7pRec4AKeRqqe4i7B40QM",
          "MileageCost": 19000,
          "RemainingSeats": 9,
          "Stops": 1,
          "TotalDuration": 535,
          "TotalTaxes": 2050
        }
      ],
      "CreatedAt": "2025-09-18T00:05:40.40668Z",
      "Date": "2026-09-05",
      "FAirlines": "",
      "FAirlinesRaw": "",
      "FAvailable": false,
      "FAvailableRaw": false,
      "FDirect": false,
      "FDirectAirlines": "",
      "FDirectAirlinesRaw": "",
      "FDirectMileageCost": 0,
      "FDirectMileageCostRaw": 0,
      "FDirectRaw": false,
      "FDirectRemainingSeats": 0,
      "FDirectRemainingSeatsRaw": 0,
      "FDirectTotalTaxes": 0,
      "FDirectTotalTaxesRaw": 0,
      "FMileageCost": "0",
      "FMileageCostRaw": 0,
      "FRemainingSeats": 0,
      "FRemainingSeatsRaw": 0,
      "FTotalTaxes": 0,
      "FTotalTaxesRaw": 0,
      "ID": "32qhZ530xETR57J6czXefZfujys",
      "JAirlines": "",
      "JAirlinesRaw": "",
      "JAvailable": false,
      "JAvailableRaw": false,
      "JDirect": false,
      "JDirectAirlines": "",
      "JDirectAirlinesRaw": "",
      "JDirectMileageCost": 0,
      "JDirectMileageCostRaw": 0,
      "JDirectRaw": false,
      "JDirectRemainingSeats": 0,
      "JDirectRemainingSeatsRaw": 0,
      "JDirectTotalTaxes": 0,
      "JDirectTotalTaxesRaw": 0,
      "JMileageCost": "0",
      "JMileageCostRaw": 0,
      "JRemainingSeats": 0,
      "JRemainingSeatsRaw": 0,
      "JTotalTaxes": 0,
      "JTotalTaxesRaw": 0,
      "ParsedDate": "2026-09-05T00:00:00Z",
      "Route": {
        "DestinationAirport": "MSO",
        "DestinationRegion": "North America",
        "Distance": 769,
        "ID": "2caRKeabBuYiJUYG2lnUzW4qnDt",
        "OriginAirport": "SFO",
        "OriginRegion": "North America",
        "Source": "velocity"
      },
      "RouteID": "2caRKeabBuYiJUYG2lnUzW4qnDt",
      "Source": "velocity",
      "TaxesCurrency": "AUD",
      "UpdatedAt": "2026-04-28T10:02:17.789234Z",
      "WAirlines": "",
      "WAirlinesRaw": "",
      "WAvailable": false,
      "WAvailableRaw": false,
      "WDirect": false,
      "WDirectAirlines": "",
      "WDirectAirlinesRaw": "",
      "WDirectMileageCost": 0,
      "WDirectMileageCostRaw": 0,
      "WDirectRaw": false,
      "WDirectRemainingSeats": 0,
      "WDirectRemainingSeatsRaw": 0,
      "WDirectTotalTaxes": 0,
      "WDirectTotalTaxesRaw": 0,
      "WMileageCost": "0",
      "WMileageCostRaw": 0,
      "WRemainingSeats": 0,
      "WRemainingSeatsRaw": 0,
      "WTotalTaxes": 0,
      "WTotalTaxesRaw": 0,
      "YAirlines": "UA",
      "YAirlinesRaw": "UA",
      "YAvailable": true,
      "YAvailableRaw": true,
      "YDirect": false,
      "YDirectAirlines": "",
      "YDirectAirlinesRaw": "",
      "YDirectMileageCost": 0,
      "YDirectMileageCostRaw": 0,
      "YDirectRaw": false,
      "YDirectRemainingSeats": 0,
      "YDirectRemainingSeatsRaw": 0,
      "YDirectTotalTaxes": 0,
      "YDirectTotalTaxesRaw": 0,
      "YMileageCost": "19000",
      "YMileageCostRaw": 19000,
      "YRemainingSeats": 9,
      "YRemainingSeatsRaw": 9,
      "YTotalTaxes": 2050,
      "YTotalTaxesRaw": 2050
    },
    {
      "AvailabilityTrips": [
        {
          "AvailabilityID": "32l789cPOTMixyteB9TllZswsZq",
          "Cabin": "economy",
          "Carriers": "UA",
          "ID": "3EAgJombtkv0SNS3LuOi4l8NRPp",
          "MileageCost": 15000,
          "RemainingSeats": 5,
          "Stops": 2,
          "TotalDuration": 614,
          "TotalTaxes": 4670
        },
        {
          "AvailabilityID": "32l789cPOTMixyteB9TllZswsZq",
          "Cabin": "economy",
          "Carriers": "UA",
          "ID": "3EAgJrQAUlYhhL6MvnsydLGMsbh",
          "MileageCost": 15000,
          "RemainingSeats": 9,
          "Stops": 1,
          "TotalDuration": 932,
          "TotalTaxes": 5440
        },
        {
          "AvailabilityID": "32l789cPOTMixyteB9TllZswsZq",
          "Cabin": "economy",
          "Carriers": "UA",
          "ID": "3EAgJqcLMGFt3DeaanIWQT16v9A",
          "MileageCost": 15000,
          "RemainingSeats": 9,
          "Stops": 1,
          "TotalDuration": 872,
          "TotalTaxes": 5440
        },
        {
          "AvailabilityID": "32l789cPOTMixyteB9TllZswsZq",
          "Cabin": "economy",
          "Carriers": "UA",
          "ID": "3EAgJs1rk4arkwRKnv8YfUUk0qm",
          "MileageCost": 15000,
          "RemainingSeats": 7,
          "Stops": 2,
          "TotalDuration": 729,
          "TotalTaxes": 5440
        },
        {
          "AvailabilityID": "32l789cPOTMixyteB9TllZswsZq",
          "Cabin": "economy",
          "Carriers": "UA",
          "ID": "3EAgJsPRLLTRv1O8yiefYeir9Ar",
          "MileageCost": 15000,
          "RemainingSeats": 9,
          "Stops": 1,
          "TotalDuration": 704,
          "TotalTaxes": 5440
        }
      ],
      "CreatedAt": "2025-09-16T00:35:14.78427Z",
      "Date": "2026-09-05",
      "FAirlines": "",
      "FAirlinesRaw": "",
      "FAvailable": false,
      "FAvailableRaw": false,
      "FDirect": false,
      "FDirectAirlines": "",
      "FDirectAirlinesRaw": "",
      "FDirectMileageCost": 0,
      "FDirectMileageCostRaw": 0,
      "FDirectRaw": false,
      "FDirectRemainingSeats": 0,
      "FDirectRemainingSeatsRaw": 0,
      "FDirectTotalTaxes": 0,
      "FDirectTotalTaxesRaw": 0,
      "FMileageCost": "0",
      "FMileageCostRaw": 0,
      "FRemainingSeats": 0,
      "FRemainingSeatsRaw": 0,
      "FTotalTaxes": 0,
      "FTotalTaxesRaw": 0,
      "ID": "32l789cPOTMixyteB9TllZswsZq",
      "JAirlines": "",
      "JAirlinesRaw": "",
      "JAvailable": false,
      "JAvailableRaw": false,
      "JDirect": false,
      "JDirectAirlines": "",
      "JDirectAirlinesRaw": "",
      "JDirectMileageCost": 0,
      "JDirectMileageCostRaw": 0,
      "JDirectRaw": false,
      "JDirectRemainingSeats": 0,
      "JDirectRemainingSeatsRaw": 0,
      "JDirectTotalTaxes": 0,
      "JDirectTotalTaxesRaw": 0,
      "JMileageCost": "0",
      "JMileageCostRaw": 0,
      "JRemainingSeats": 0,
      "JRemainingSeatsRaw": 0,
      "JTotalTaxes": 0,
      "JTotalTaxesRaw": 0,
      "ParsedDate": "2026-09-05T00:00:00Z",
      "Route": {
        "DestinationAirport": "MSO",
        "DestinationRegion": "North America",
        "Distance": 769,
        "ID": "2iNafxgZGSlJwoWZukyfRzE9stC",
        "OriginAirport": "SFO",
        "OriginRegion": "North America",
        "Source": "aeroplan"
      },
      "RouteID": "2iNafxgZGSlJwoWZukyfRzE9stC",
      "Source": "aeroplan",
      "TaxesCurrency": "CAD",
      "UpdatedAt": "2026-05-24T12:45:18.052434Z",
      "WAirlines": "",
      "WAirlinesRaw": "",
      "WAvailable": false,
      "WAvailableRaw": false,
      "WDirect": false,
      "WDirectAirlines": "",
      "WDirectAirlinesRaw": "",
      "WDirectMileageCost": 0,
      "WDirectMileageCostRaw": 0,
      "WDirectRaw": false,
      "WDirectRemainingSeats": 0,
      "WDirectRemainingSeatsRaw": 0,
      "WDirectTotalTaxes": 0,
      "WDirectTotalTaxesRaw": 0,
      "WMileageCost": "0",
      "WMileageCostRaw": 0,
      "WRemainingSeats": 0,
      "WRemainingSeatsRaw": 0,
      "WTotalTaxes": 0,
      "WTotalTaxesRaw": 0,
      "YAirlines": "UA",
      "YAirlinesRaw": "UA",
      "YAvailable": true,
      "YAvailableRaw": true,
      "YDirect": false,
      "YDirectAirlines": "",
      "YDirectAirlinesRaw": "",
      "YDirectMileageCost": 0,
      "YDirectMileageCostRaw": 0,
      "YDirectRaw": false,
      "YDirectRemainingSeats": 0,
      "YDirectRemainingSeatsRaw": 0,
      "YDirectTotalTaxes": 0,
      "YDirectTotalTaxesRaw": 0,
      "YMileageCost": "15000",
      "YMileageCostRaw": 15000,
      "YRemainingSeats": 9,
      "YRemainingSeatsRaw": 9,
      "YTotalTaxes": 4670,
      "YTotalTaxesRaw": 4670
    }
  ],
  "hasMore": false
}
