{
  "booking_labels_seen": [
    "Book via Air Canada Aeroplan",
    "Book via Air France/KLM Flying Blue",
    "Book via Alaska Atmos Rewards",
    "Book via American AAdvantage",
    "Book via Azul Fidelidade",
    "Book via Azul Fidelidade (Azul-operated)",
    "Book via Azul Fidelidade (business)",
    "Book via British Airways Club",
    "Book via Copa ConnectMiles",
    "Book via Delta SkyMiles",
    "Book via Finnair Plus (must login)",
    "Book via Qantas Frequent Flyer",
    "Book via Qatar Airways Privilege Club",
    "Book via United MileagePlus",
    "Book via Virgin Atlantic",
    "Book via Virgin Australia Velocity"
  ],
  "carrier_codes_seen": [
    "AA",
    "AS",
    "DL",
    "UA"
  ],
  "count": 9,
  "cursor": 1779259861,
  "has_more": false,
  "route_ids_found": [
    "2EUpHD8TRaxHoMwMU4VbGSkvAtW",
    "2IZU4tUmuXedgW3w1WqNYRbaKDX",
    "2Vf4pAO5sdf23zkMvs2U6t3E0Db",
    "2Wnm5EWlZwmueSCcojzhzLDVFpV",
    "2fLNdCE2aivlYCpzzVvLdiB7vcj",
    "2fLNdgLhAPC92DLQfg271DZe2BJ",
    "2fLNfHJWEZcFcmrPxPZYAaGF7AD",
    "2ikBvvYkT4hLrFDgEsLwsY7ae8n",
    "2ikEyLtsvwIGnLDtZhbk2xymByE"
  ],
  "rows": [
    {
      "availability_id": "35d3qfoi7xigdLJBusf1xedemvm",
      "business_available": true,
      "business_miles": 59900,
      "business_taxes": 560,
      "date": "2026-10-14",
      "destination": "DTW",
      "direct_business_available": true,
      "direct_economy_available": true,
      "economy_available": true,
      "economy_miles": 31700,
      "economy_taxes": 560,
      "first_available": false,
      "origin": "SFO",
      "premium_available": false,
      "source": "delta",
      "taxes_currency": "USD",
      "trip_count": 25
    },
    {
      "availability_id": "35d3agNuhIrBizGmijeaDnZosJS",
      "business_available": true,
      "business_miles": 43000,
      "business_taxes": 1120,
      "date": "2026-10-14",
      "destination": "DTW",
      "direct_business_available": false,
      "direct_economy_available": false,
      "economy_available": true,
      "economy_miles": 9500,
      "economy_taxes": 560,
      "first_available": false,
      "origin": "SFO",
      "premium_available": false,
      "source": "american",
      "taxes_currency": "USD",
      "trip_count": 66
    },
    {
      "availability_id": "34dZ9nQVJu3CUNPIu40j4Yp5eVU",
      "business_available": true,
      "business_miles": 47500,
      "business_taxes": 560,
      "date": "2026-10-14",
      "destination": "DTW",
      "direct_business_available": false,
      "direct_economy_available": false,
      "economy_available": true,
      "economy_miles": 15000,
      "economy_taxes": 1810,
      "first_available": false,
      "origin": "SFO",
      "premium_available": false,
      "source": "alaska",
      "taxes_currency": "USD",
      "trip_count": 41
    },
    {
      "availability_id": "34Y9SE3NTB86pm0qPfJqMP9qViN",
      "business_available": false,
      "business_miles": 0,
      "business_taxes": 0,
      "date": "2026-10-14",
      "destination": "DTW",
      "direct_business_available": false,
      "direct_economy_available": true,
      "economy_available": true,
      "economy_miles": 15000,
      "economy_taxes": 4670,
      "first_available": false,
      "origin": "SFO",
      "premium_available": false,
      "source": "aeroplan",
      "taxes_currency": "CAD",
      "trip_count": 4
    },
    {
      "availability_id": "358U1VDnG7iFwITodWhEWFzWKC5",
      "business_available": false,
      "business_miles": 0,
      "business_taxes": 0,
      "date": "2026-10-14",
      "destination": "DTW",
      "direct_business_available": false,
      "direct_economy_available": true,
      "economy_available": true,
      "economy_miles": 16000,
      "economy_taxes": 2044,
      "first_available": false,
      "origin": "SFO",
      "premium_available": false,
      "source": "flyingblue",
      "taxes_currency": "USD",
      "trip_count": 6
    },
    {
      "availability_id": "35d3YcK7sFMcCXcDTYBQPmeHtMG",
      "business_available": false,
      "business_miles": 0,
      "business_taxes": 0,
      "date": "2026-10-14",
      "destination": "DTW",
      "direct_business_available": false,
      "direct_economy_available": true,
      "economy_available": true,
      "economy_miles": 22000,
      "economy_taxes": 560,
      "first_available": false,
      "origin": "SFO",
      "premium_available": false,
      "source": "virginatlantic",
      "taxes_currency": "USD",
      "trip_count": 5
    },
    {
      "availability_id": "34dZKhmd44E5SskHLkPZHXwKhFs",
      "business_available": false,
      "business_miles": 0,
      "business_taxes": 0,
      "date": "2026-10-14",
      "destination": "DTW",
      "direct_business_available": false,
      "direct_economy_available": true,
      "economy_available": true,
      "economy_miles": 19000,
      "economy_taxes": 1420,
      "first_available": false,
      "origin": "SFO",
      "premium_available": false,
      "source": "velocity",
      "taxes_currency": "AUD",
      "trip_count": 4
    },
    {
      "availability_id": "35d3b2wTLJwcn5oEDWfI4JnOtUi",
      "business_available": false,
      "business_miles": 0,
      "business_taxes": 0,
      "date": "2026-10-14",
      "destination": "DTW",
      "direct_business_available": false,
      "direct_economy_available": true,
      "economy_available": true,
      "economy_miles": 18315,
      "economy_taxes": 2267,
      "first_available": false,
      "origin": "SFO",
      "premium_available": false,
      "source": "azul",
      "taxes_currency": "BRL",
      "trip_count": 9
    },
    {
      "availability_id": "35Rj1XR82DWrdaECgqzAdK9i3em",
      "business_available": false,
      "business_miles": 58300,
      "business_taxes": 560,
      "date": "2026-10-14",
      "destination": "DTW",
      "direct_business_available": false,
      "direct_economy_available": true,
      "economy_available": true,
      "economy_miles": 15000,
      "economy_taxes": 560,
      "first_available": false,
      "origin": "SFO",
      "premium_available": false,
      "source": "united",
      "taxes_currency": "USD",
      "trip_count": 37
    }
  ],
  "sources_found": [
    "aeroplan",
    "alaska",
    "american",
    "azul",
    "delta",
    "flyingblue",
    "united",
    "velocity",
    "virginatlantic"
  ]
}